terraform_ingest/__init__.py
terraform_ingest/_version.py
terraform_ingest/api.py
terraform_ingest/cli.py
terraform_ingest/dependency_installer.py
terraform_ingest/embeddings.py
terraform_ingest/importers.py
terraform_ingest/indexer.py
terraform_ingest/ingest.py
terraform_ingest/mcp_service.py
terraform_ingest/models.py
terraform_ingest/old-logging.py
terraform_ingest/parser.py
terraform_ingest/repository.py
terraform_ingest/tty_logger.py
terraform_ingest/validate_server.py
terraform_ingest-0.1.21.dist-info/METADATA
terraform_ingest-0.1.21.dist-info/WHEEL
terraform_ingest-0.1.21.dist-info/entry_points.txt
terraform_ingest-0.1.21.dist-info/licenses/LICENSE
terraform_ingest-0.1.21.dist-info/RECORD
