Metadata-Version: 2.4
Name: terraform-ingest
Version: 0.1.21
Summary: A terraform multi-repo module AI RAG ingestion engine that accepts a YAML file of terraform git repository sources, downloads them locally using existing credentials, creates JSON summaries of their purpose, inputs, outputs, and providers on the main and git tag branches for ingestion via a RAG pipeline into a vector database.
Author-email: Zachary Loeber <zloeber@gmail.com>
License-File: LICENSE
Classifier: Operating System :: OS Independent
Classifier: Programming Language :: Python :: 3
Requires-Python: >=3.12
Requires-Dist: click>=8.3.0
Requires-Dist: fastapi>=0.119.0
Requires-Dist: fastmcp>=0.5.0
Requires-Dist: gitpython>=3.1.45
Requires-Dist: httpx>=0.28.1
Requires-Dist: loguru>=0.7.3
Requires-Dist: packaging>=24.0
Requires-Dist: pydantic>=2.12.2
Requires-Dist: python-hcl2>=7.3.1
Requires-Dist: pyyaml>=6.0.3
Requires-Dist: urllib3>=2.5.0
Requires-Dist: uvicorn>=0.37.0
Provides-Extra: dev
Requires-Dist: black; extra == 'dev'
Requires-Dist: isort; extra == 'dev'
Requires-Dist: mypy; extra == 'dev'
Requires-Dist: ruff; extra == 'dev'
Provides-Extra: docs
Requires-Dist: mdtoc; extra == 'docs'
Requires-Dist: mkdocs; extra == 'docs'
Requires-Dist: mkdocs-click; extra == 'docs'
Requires-Dist: mkdocs-llmstxt; extra == 'docs'
Requires-Dist: mkdocs-material; extra == 'docs'
Requires-Dist: mkdocs-mermaid2-plugin; extra == 'docs'
Requires-Dist: mkdocstrings; extra == 'docs'
Provides-Extra: embeddings
Requires-Dist: chromadb>=1.2.1; extra == 'embeddings'
Requires-Dist: openai>=1.0.0; extra == 'embeddings'
Requires-Dist: sentence-transformers>=5.1.2; extra == 'embeddings'
Requires-Dist: voyageai>=0.2.0; extra == 'embeddings'
Provides-Extra: format
Requires-Dist: black; extra == 'format'
Requires-Dist: isort; extra == 'format'
Provides-Extra: lint
Requires-Dist: black; extra == 'lint'
Requires-Dist: isort; extra == 'lint'
Requires-Dist: mypy; extra == 'lint'
Requires-Dist: ruff; extra == 'lint'
Provides-Extra: standard
Provides-Extra: test
Requires-Dist: black; extra == 'test'
Requires-Dist: httpx; extra == 'test'
Requires-Dist: mypy; extra == 'test'
Requires-Dist: pytest; extra == 'test'
Requires-Dist: pytest-asyncio; extra == 'test'
Requires-Dist: pytest-cov; extra == 'test'
Requires-Dist: ruff; extra == 'test'
Provides-Extra: typecheck
Requires-Dist: mypy; extra == 'typecheck'
